{"type":"node_created","timestamp":"2026-01-17T21:32:04.405003986Z","node":{"id":"1.2","type":"claim","statement":"PART 1 - INVERSE OF c_13 (citing Three_Cycle_Inverse): c_13 = (1 5 6)(2 3 4). Each 3-cycle inverts by reversing: (1 5 6)^{-1} = (1 6 5), (2 3 4)^{-1} = (2 4 3). Thus c_13^{-1} = (1 6 5)(2 4 3).","inference":"assumption","workflow_state":"available","epistemic_state":"pending","taint_state":"unresolved","content_hash":"138023bea2e528c029fa071cca104f4012695b87f0239c258fdd2b3e1a48a857","created":"2026-01-17T21:32:04.404993006Z","claimed_at":"0001-01-01T00:00:00Z"}}