{"type":"node_created","timestamp":"2026-02-11T17:22:09.583605899Z","node":{"id":"1","type":"claim","statement":"The Biggs-Lin-Maldacena melonic quantum mechanical model (arXiv:2601.08908) admits a consistent quantum group generalization: replacing the SU(2) Wigner 3j coupling coefficients with U_q(su(2)) quantum Clebsch-Gordan coefficients yields a well-defined Hamiltonian H_q = {Q_q, Q_q†} that (1) preserves N=2 supersymmetry and positive semi-definiteness for q \u003e 0 real, (2) exhibits melonic dominance in the large-j limit via quantum 3j orthogonality, (3) admits q-deformed BPS states with degeneracy computable from the q-Witten index, and (4) connects in the large-j semiclassical limit to Turaev-Viro 3D topological invariants (generalizing the Ponzano-Regge connection of the original model).","inference":"assumption","workflow_state":"available","epistemic_state":"pending","taint_state":"unresolved","content_hash":"dde4941318b5fceafd196fae2ab402df4b1bda7d88214ae22ee9a8a4fd7748c4","created":"2026-02-11T17:22:09.583591648Z","claimed_at":"0001-01-01T00:00:00Z"}}