{"type":"node_created","timestamp":"2026-01-17T14:48:03.493961684Z","node":{"id":"1.2","type":"claim","statement":"Part 1: h_1 = (1 6 4 3) permutes B_0. We compute the image of each block:\n- For {1,4}: h_1(1) = 6 and h_1(4) = 3, so h_1({1,4}) = {6,3} = {3,6}.\n- For {2,5}: h_1(2) = 2 and h_1(5) = 5 (since 2,5 are not in the cycle), so h_1({2,5}) = {2,5}.\n- For {3,6}: h_1(3) = 1 and h_1(6) = 4, so h_1({3,6}) = {1,4}.\nThus h_1 maps B_0 to itself: {1,4} -\u003e {3,6}, {2,5} -\u003e {2,5}, {3,6} -\u003e {1,4}.","inference":"assumption","workflow_state":"available","epistemic_state":"pending","taint_state":"unresolved","content_hash":"d476c647c55f71d018e1a4c667180f4c09809b4fe77b48bec858b683a1c26a51","created":"2026-01-17T14:48:03.493945459Z","claimed_at":"0001-01-01T00:00:00Z"}}