{"type":"def_added","timestamp":"2026-02-07T21:12:34.366635634Z","definition":{"id":"111a062617f18f4d","name":"entropy","definition":"Von Neumann entropy: S(rho) := -Tr[rho log rho] (natural log, 0 log 0 := 0). Conditional entropy: H(A|B)_rho := S(rho_AB) - S(rho_B). Relative entropy (Umegaki): D(rho||sigma) := Tr[rho(log rho - log sigma)] when supp(rho) ⊆ supp(sigma), else +∞. Binary entropy: h_2(eps) := -eps log eps - (1-eps) log(1-eps). Key identity CE-RE: H(A|B)_rho = -D(rho_AB || 1_A ⊗ rho_B).","created":"2026-02-07T21:12:34.365970421Z"}}